pcapfex/__init__.py
pcapfex/core/FileScanner.py
pcapfex/core/Utils.py
pcapfex/core/__init__.py
pcapfex/core/Files/FileManager.py
pcapfex/core/Files/FileObject.py
pcapfex/core/Files/__init__.py
pcapfex/core/Plugins/DataRecognizer.py
pcapfex/core/Plugins/Decoder.py
pcapfex/core/Plugins/EntropyClassifier.py
pcapfex/core/Plugins/Plugin.py
pcapfex/core/Plugins/PluginManager.py
pcapfex/core/Plugins/ProtocolDissector.py
pcapfex/core/Plugins/__init__.py
pcapfex/core/Streams/PacketStream.py
pcapfex/core/Streams/StreamBuilder.py
pcapfex/core/Streams/TCPStream.py
pcapfex/core/Streams/UDPStream.py
pcapfex/core/Streams/__init__.py
pcapfex/core/ThreadPool/Pool.py
pcapfex/core/ThreadPool/Worker.py
pcapfex/core/ThreadPool/__init__.py
pcapfex/core/Visualizations/__init__.py
pcapfex/plugins/__init__.py
pcapfex/plugins/data_recognizers/__init__.py
pcapfex/plugins/data_recognizers/avi.py
pcapfex/plugins/data_recognizers/bmp.py
pcapfex/plugins/data_recognizers/elf.py
pcapfex/plugins/data_recognizers/exe.py
pcapfex/plugins/data_recognizers/gif.py
pcapfex/plugins/data_recognizers/jpeg.py
pcapfex/plugins/data_recognizers/mkv.py
pcapfex/plugins/data_recognizers/mp3.py
pcapfex/plugins/data_recognizers/mpg.py
pcapfex/plugins/data_recognizers/pdf.py
pcapfex/plugins/data_recognizers/png.py
pcapfex/plugins/data_recognizers/rar.py
pcapfex/plugins/data_recognizers/wav.py
pcapfex/plugins/data_recognizers/zip.py
pcapfex/plugins/decoders/__init__.py
pcapfex/plugins/decoders/base64data.py
pcapfex/plugins/decoders/plaindata.py
pcapfex/plugins/protocol_dissectors/__init__.py
pcapfex/plugins/protocol_dissectors/http10.py
pcapfex/plugins/protocol_dissectors/http11.py
pcapfex/plugins/protocol_dissectors/unknown.py
pcapfex-1.0.3.dist-info/METADATA
pcapfex-1.0.3.dist-info/WHEEL
pcapfex-1.0.3.dist-info/top_level.txt
pcapfex-1.0.3.dist-info/RECORD
