Metadata-Version: 2.1
Name: pcapfex
Version: 1.0.3
Summary: Extract file from pcap file
Home-page: https://github.com/123zoeyyy/pcapfex
Author: 123zoeyyy
Author-email: yzou10@uoguelph.ca
License: MIT
Platform: UNKNOWN
Classifier: Development Status :: 4 - Beta
Classifier: Intended Audience :: Developers
Classifier: Topic :: System :: Logging
Classifier: License :: OSI Approved :: MIT License
Classifier: Programming Language :: Python :: 3
Classifier: Programming Language :: Python :: 3.3
Classifier: Programming Language :: Python :: 3.4
Classifier: Programming Language :: Python :: 3.5
Classifier: Programming Language :: Python :: 3.6
Classifier: Programming Language :: Python :: 3.7
Classifier: Programming Language :: Python :: 3.8
Requires-Dist: dpkt
Requires-Dist: regex
